distribute_setup.py
gloss.py
setup.py
wikigloss.egg-info/PKG-INFO
wikigloss.egg-info/SOURCES.txt
wikigloss.egg-info/dependency_links.txt
wikigloss.egg-info/requires.txt
wikigloss.egg-info/top_level.txt