Metadata-Version: 1.0
Name: wikigloss
Version: 0.1
Summary: Wikipedia glossary generator
Home-page: http://ericg.us
Author: Eric Gustavson
Author-email: gustavson.eric@gmail.com
License: UNKNOWN
Keywords: wikipedia glossary nlp
Platform: UNKNOWN
